ml_razor/__init__.py
ml_razor/razor.py
ml_razor-0.1.0.dist-info/METADATA
ml_razor-0.1.0.dist-info/WHEEL
ml_razor-0.1.0.dist-info/top_level.txt
ml_razor-0.1.0.dist-info/RECORD
