Metadata-Version: 2.1
Name: ml-razor
Version: 0.1.0
Summary: Tool for minimizing amount of features, while keeping model performance high.
Home-page: https://ml-razor.readthedocs.io/
Author: Jurriaan Oudenaarden
Author-email: jurriaanoudenaarden@gmail.com
License: MIT
Platform: UNKNOWN
Classifier: Intended Audience :: Developers
Classifier: License :: OSI Approved :: MIT License
Classifier: Programming Language :: Python
Classifier: Programming Language :: Python :: 3
Classifier: Programming Language :: Python :: 3.6
Classifier: Programming Language :: Python :: 3.7
Classifier: Programming Language :: Python :: 3.8
Classifier: Programming Language :: Python :: 3.9
Classifier: Operating System :: OS Independent
Requires-Dist: numpy
Requires-Dist: pandas
Requires-Dist: scipy
Requires-Dist: matplotlib
Requires-Dist: sklearn
